skrmt/__init__.py
skrmt/covariance/__init__.py
skrmt/covariance/estimator.py
skrmt/covariance/metrics.py
skrmt/covariance/tests/__init__.py
skrmt/covariance/tests/test_estimator.py
skrmt/covariance/tests/test_metrics.py
skrmt/ensemble/__init__.py
skrmt/ensemble/_base_ensemble.py
skrmt/ensemble/circular_ensemble.py
skrmt/ensemble/gaussian_ensemble.py
skrmt/ensemble/manova_ensemble.py
skrmt/ensemble/plot_law.py
skrmt/ensemble/tridiagonal_utils.py
skrmt/ensemble/wishart_ensemble.py
skrmt/ensemble/tests/__init__.py
skrmt/ensemble/tests/test_circular_ens.py
skrmt/ensemble/tests/test_gaussian_ens.py
skrmt/ensemble/tests/test_manova_ens.py
skrmt/ensemble/tests/test_tridiagonalization.py
skrmt/ensemble/tests/test_wishart_ens.py
scikit_rmt-0.2.dist-info/LICENSE
scikit_rmt-0.2.dist-info/METADATA
scikit_rmt-0.2.dist-info/WHEEL
scikit_rmt-0.2.dist-info/top_level.txt
scikit_rmt-0.2.dist-info/RECORD
