Metadata-Version: 2.1
Name: scikit-rmt
Version: 0.2
Summary: Random Matrix Theory Python package
Home-page: https://github.com/AlejandroSantorum/scikit-rmt
Author: Alejandro Santorum Varela
Author-email: alejandro.santorum@gmail.com
License: BSD
Download-URL: https://github.com/AlejandroSantorum/scikit-rmt/archive/refs/tags/v0.2.tar.gz
Keywords: RMT,Random Matrix Theory,Ensemble,Covariance matrices
Platform: UNKNOWN
Classifier: Development Status :: 3 - Alpha
Classifier: Intended Audience :: Developers
Classifier: Intended Audience :: Science/Research
Classifier: License :: OSI Approved :: BSD License
Classifier: Natural Language :: English
Classifier: Operating System :: OS Independent
Classifier: Programming Language :: Python :: 3.7
Classifier: Programming Language :: Python :: 3.8
Classifier: Topic :: Scientific/Engineering :: Mathematics
Classifier: Topic :: Software Development :: Libraries :: Python Modules
